[
  {
    "title": "transform",
    "family": "core",
    "description": "The `transform` property applies a 2D or 3D transformation to an element.",
    "responsive": false,
    "pseudos": [
      "hover",
      "active",
      "group-hover"
    ],
    "classes": [
      {
        "class": "`.transform translate-x-0`",
        "properties": [
          "`transform: translateX(0);`"
        ]
      },
      {
        "class": "`.transform translate-x-1`",
        "properties": [
          "`transform: translateX(0.25rem);`"
        ]
      },
      {
        "class": "`.transform translate-x-2`",
        "properties": [
          "`transform: translateX(0.5rem);`"
        ]
      },
      {
        "class": "`.transform translate-x-3`",
        "properties": [
          "`transform: translateX(0.75rem);`"
        ]
      },
      {
        "class": "`.transform translate-x-n1`",
        "properties": [
          "`transform: translateX(-0.25rem);`"
        ]
      },
      {
        "class": "`.transform translate-x-n2`",
        "properties": [
          "`transform: translateX(-0.5rem);`"
        ]
      },
      {
        "class": "`.transform translate-x-n3`",
        "properties": [
          "`transform: translateX(-0.75rem);`"
        ]
      },
      {
        "class": "`.transform-y-0`",
        "properties": [
          "`transform: translateY(0);`"
        ]
      },
      {
        "class": "`.transform-y-1`",
        "properties": [
          "`transform: translateY(0.25rem);`"
        ]
      },
      {
        "class": "`.transform-y-2`",
        "properties": [
          "`transform: translateY(0.5rem);`"
        ]
      },
      {
        "class": "`.transform-y-3`",
        "properties": [
          "`transform: translateY(0.75rem);`"
        ]
      },
      {
        "class": "`.transform-y-n1`",
        "properties": [
          "`transform: translateY(-0.25rem);`"
        ]
      },
      {
        "class": "`.transform-y-n2`",
        "properties": [
          "`transform: translateY(-0.5rem);`"
        ]
      },
      {
        "class": "`.transform-y-n3`",
        "properties": [
          "`transform: translateY(-0.75rem);`"
        ]
      },
      {
        "class": "`.transform-rotate-0`",
        "properties": [
          "`transform: rotate(0);`"
        ]
      },
      {
        "class": "`.transform-rotate-45`",
        "properties": [
          "`transform: rotate(45deg);`"
        ]
      },
      {
        "class": "`.transform-rotate-90`",
        "properties": [
          "`transform: rotate(90deg);`"
        ]
      },
      {
        "class": "`.transform-rotate-180`",
        "properties": [
          "`transform: rotate(180deg);`"
        ]
      },
      {
        "class": "`.transform-size-n1`",
        "properties": [
          "`transform: scale(0.7);`"
        ]
      },
      {
        "class": "`.transform-size-n2`",
        "properties": [
          "`transform: scale(0.8);`"
        ]
      },
      {
        "class": "`.transform-size-n3`",
        "properties": [
          "`transform: scale(0.9);`"
        ]
      },
      {
        "class": "`.transform-size-0`",
        "properties": [
          "`transform: scale(1);`"
        ]
      },
      {
        "class": "`.transform-size-1`",
        "properties": [
          "`transform: scale(1.1);`"
        ]
      },
      {
        "class": "`.transform-size-2`",
        "properties": [
          "`transform: scale(1.2);`"
        ]
      },
      {
        "class": "`.transform-size-3`",
        "properties": [
          "`transform: scale(1.3);`"
        ]
      }
    ]
  },
  {
    "title": "transform-origin",
    "family": "core",
    "description": "The `transform-origin` property allows you to change the position of transformed elements.",
    "responsive": false,
    "pseudos": [
      "none"
    ],
    "classes": [
      {
        "class": "`.transform-center`",
        "properties": [
          "`transform-origin: center;`"
        ]
      },
      {
        "class": "`.transform-top`",
        "properties": [
          "`transform-origin: top;`"
        ]
      },
      {
        "class": "`.transform-top-right`",
        "properties": [
          "`transform-origin: top right;`"
        ]
      },
      {
        "class": "`.transform-right`",
        "properties": [
          "`transform-origin: right;`"
        ]
      },
      {
        "class": "`.transform-bottom-right`",
        "properties": [
          "`transform-origin: bottom right;`"
        ]
      },
      {
        "class": "`.transform-bottom`",
        "properties": [
          "`transform-origin: bottom;`"
        ]
      },
      {
        "class": "`.transform-bottom-left`",
        "properties": [
          "`transform-origin: bottom left;`"
        ]
      },
      {
        "class": "`.transform-left`",
        "properties": [
          "`transform-origin: left;`"
        ]
      },
      {
        "class": "`.transform-top-left`",
        "properties": [
          "`transform-origin: top left;`"
        ]
      }
    ]
  },
  {
    "title": "translate-x",
    "family": "core",
    "description": "The `transform-origin` property allows you to change the position of transformed elements.",
    "responsive": false,
    "pseudos": [
      "none"
    ],
    "classes": [
      {
        "class": "`.transform-center`",
        "properties": [
          "`transform-origin: center;`"
        ]
      }
    ]
  },
  {
    "title": "translate-y",
    "family": "core",
    "description": "The `transform-origin` property allows you to change the position of transformed elements.",
    "responsive": false,
    "pseudos": [
      "none"
    ],
    "classes": [
      {
        "class": "`.transform-center`",
        "properties": [
          "`transform-origin: center;`"
        ]
      }
    ]
  },
  {
    "title": "scale-x",
    "family": "core",
    "description": "The `transform-origin` property allows you to change the position of transformed elements.",
    "responsive": false,
    "pseudos": [
      "none"
    ],
    "classes": [
      {
        "class": "`.transform-center`",
        "properties": [
          "`transform-origin: center;`"
        ]
      }
    ]
  },
  {
    "title": "scale-y",
    "family": "core",
    "description": "The `transform-origin` property allows you to change the position of transformed elements.",
    "responsive": false,
    "pseudos": [
      "none"
    ],
    "classes": [
      {
        "class": "`.transform-center`",
        "properties": [
          "`transform-origin: center;`"
        ]
      }
    ]
  },
  {
    "title": "skew-x",
    "family": "core",
    "description": "The `transform-origin` property allows you to change the position of transformed elements.",
    "responsive": false,
    "pseudos": [
      "none"
    ],
    "classes": [
      {
        "class": "`.transform-center`",
        "properties": [
          "`transform-origin: center;`"
        ]
      }
    ]
  },
  {
    "title": "skew-y",
    "family": "core",
    "description": "The `transform-origin` property allows you to change the position of transformed elements.",
    "responsive": false,
    "pseudos": [
      "none"
    ],
    "classes": [
      {
        "class": "`.transform-center`",
        "properties": [
          "`transform-origin: center;`"
        ]
      }
    ]
  },
  {
    "title": "rotate",
    "family": "core",
    "description": "The `transform-origin` property allows you to change the position of transformed elements.",
    "responsive": false,
    "pseudos": [
      "none"
    ],
    "classes": [
      {
        "class": "`.transform-center`",
        "properties": [
          "`transform-origin: center;`"
        ]
      }
    ]
  }
]